[
  {
    "Job_Name": 15212,
    "Job_Owner": "z5358697@katana2",
    "job_state": "Q",
    "queue": "cstudent12",
    "server": "kman",
    "Checkpoint": "u",
    "ctime": "Sun Jun 29 00:45:58 2025",
    "Error_Path": "katana2:/srv/scratch/z5358697/.automated/15212/15212.e6652787",
    "Hold_Types": "n",
    "Join_Path": "oe",
    "Keep_Files": "n",
    "Mail_Points": "a",
    "mtime": "Sun Jun 29 00:45:58 2025",
    "Output_Path": "katana2:/srv/scratch/z5358697/.automated/15212/15212.o6652787",
    "Priority": 0,
    "qtime": "Sun Jun 29 00:45:58 2025",
    "Rerunable": "True",
    "Resource_List": {
      "ib": "no",
      "mem": "4gb",
      "ncpus": 1,
      "ngpus": 0,
      "nodect": 1,
      "place": "group=cstudent12",
      "select": "ncpus=1:mem=4gb",
      "walltime": "12:00:00"
    },
    "substate": 10,
    "Variable_List": {
      "PBS_O_HOME": "/home/z5358697",
      "PBS_O_LANG": "en_AU.UTF-8",
      "PBS_O_LOGNAME": "z5358697",
      "PBS_O_PATH": "/apps/z_install_tree/linux-rocky8-ivybridge/gcc-12.2.0/python-3.10.8-pmtwsrrmcmrs6olvgx5xhepgh7gl5vro/bin:/home/z5358697/bin:/home/z5358697/bin:/usr/share/Modules/bin:/usr/lib64/ccache:/usr/local/bin:/usr/bin:/usr/local/sbin:/usr/sbin:/opt/pbs/bin",
      "PBS_O_SHELL": "/bin/bash",
      "PBS_O_WORKDIR": "/srv/scratch/z5358697/.automated/15212",
      "PBS_O_SYSTEM": "Linux",
      "PBS_O_QUEUE": "cstudent12",
      "PBS_O_HOST": "katana2"
    },
    "etime": "Sun Jun 29 00:45:58 2025",
    "eligible_time": "00:00:18",
    "Submit_arguments": "-N 15212 /tmp/15212.mIatuxq",
    "project": "_pbs_project_default",
    "Submit_Host": "katana2"
  }
]
