[
  {
    "Job_Name": 10126,
    "Job_Owner": "z5382435@katana3",
    "resources_used": {
      "cpupercent": 1168,
      "cput": "17:10:41",
      "fs_usage": 1020,
      "mem": "286820kb",
      "ncpus": 12,
      "vmem": "286820kb",
      "walltime": "01:26:37"
    },
    "job_state": "R",
    "queue": "generalgpu12",
    "server": "kman",
    "Checkpoint": "u",
    "ctime": "Mon May  5 07:17:39 2025",
    "Error_Path": "katana3:/srv/scratch/z5382435/.automated/10126/10126.e6495020",
    "exec_host": "k175/1*12",
    "exec_vnode": "(k175:ncpus=12:ngpus=1:mem=1048576kb)",
    "Hold_Types": "n",
    "Join_Path": "oe",
    "Keep_Files": "n",
    "Mail_Points": "a",
    "mtime": "Mon May  5 10:58:59 2025",
    "Output_Path": "katana3:/srv/scratch/z5382435/.automated/10126/10126.o6495020",
    "Priority": 0,
    "qtime": "Mon May  5 07:17:39 2025",
    "Rerunable": "True",
    "Resource_List": {
      "ib": "no",
      "mem": "1gb",
      "ncpus": 12,
      "ngpus": 1,
      "nodect": 1,
      "place": "group=generalgpu12",
      "select": "ncpus=12:ngpus=1:mem=1gb",
      "walltime": "12:00:00"
    },
    "stime": "Mon May  5 09:32:19 2025",
    "session_id": 738504,
    "jobdir": "/home/z5382435",
    "substate": 42,
    "Variable_List": {
      "PBS_O_HOME": "/home/z5382435",
      "PBS_O_LANG": "en_AU.UTF-8",
      "PBS_O_LOGNAME": "z5382435",
      "PBS_O_PATH": "/srv/scratch/z5382435/anaconda3/bin:/home/z5382435/bin:/usr/share/Modules/bin:/usr/lib64/ccache:/usr/local/bin:/usr/bin:/usr/local/sbin:/usr/sbin:/opt/pbs/bin",
      "PBS_O_SHELL": "/bin/bash",
      "PBS_O_WORKDIR": "/srv/scratch/z5382435/.automated/10126",
      "PBS_O_SYSTEM": "Linux",
      "PBS_O_QUEUE": "generalgpu12",
      "PBS_O_HOST": "katana3",
      "nvidia_group_id": 630
    },
    "comment": "Job run at Mon May 05 at 09:32 on (k175:ncpus=12:ngpus=1:mem=1048576kb)",
    "etime": "Mon May  5 07:17:39 2025",
    "run_count": 1,
    "eligible_time": "02:14:44",
    "Submit_arguments": "-N 10126 /tmp/10126.1jLKBqK",
    "estimated": {
      "exec_vnode": "(k175:ncpus=12:ngpus=1:mem=1048576kb)",
      "start_time": "Mon May  5 09:39:52 2025"
    },
    "project": "_pbs_project_default",
    "Submit_Host": "katana3"
  },
  {
    "Job_Name": 10128,
    "Job_Owner": "z5382435@katana3",
    "resources_used": {
      "cpupercent": 1164,
      "cput": "15:04:28",
      "fs_usage": 900,
      "mem": "263620kb",
      "ncpus": 12,
      "vmem": "263620kb",
      "walltime": "01:16:34"
    },
    "job_state": "R",
    "queue": "generalgpu12",
    "server": "kman",
    "Checkpoint": "u",
    "ctime": "Mon May  5 07:28:55 2025",
    "Error_Path": "katana3:/srv/scratch/z5382435/.automated/10128/10128.e6495023",
    "exec_host": "k172/3*12",
    "exec_vnode": "(k172:ncpus=12:ngpus=1:mem=1048576kb)",
    "Hold_Types": "n",
    "Join_Path": "oe",
    "Keep_Files": "n",
    "Mail_Points": "a",
    "mtime": "Mon May  5 10:58:53 2025",
    "Output_Path": "katana3:/srv/scratch/z5382435/.automated/10128/10128.o6495023",
    "Priority": 0,
    "qtime": "Mon May  5 07:28:56 2025",
    "Rerunable": "True",
    "Resource_List": {
      "ib": "no",
      "mem": "1gb",
      "ncpus": 12,
      "ngpus": 1,
      "nodect": 1,
      "place": "group=generalgpu12",
      "select": "ncpus=12:ngpus=1:mem=1gb",
      "walltime": "12:00:00"
    },
    "stime": "Mon May  5 09:42:17 2025",
    "session_id": 601601,
    "jobdir": "/home/z5382435",
    "substate": 42,
    "Variable_List": {
      "PBS_O_HOME": "/home/z5382435",
      "PBS_O_LANG": "en_AU.UTF-8",
      "PBS_O_LOGNAME": "z5382435",
      "PBS_O_PATH": "/srv/scratch/z5382435/anaconda3/bin:/home/z5382435/bin:/usr/share/Modules/bin:/usr/lib64/ccache:/usr/local/bin:/usr/bin:/usr/local/sbin:/usr/sbin:/opt/pbs/bin",
      "PBS_O_SHELL": "/bin/bash",
      "PBS_O_WORKDIR": "/srv/scratch/z5382435/.automated/10128",
      "PBS_O_SYSTEM": "Linux",
      "PBS_O_QUEUE": "generalgpu12",
      "PBS_O_HOST": "katana3",
      "nvidia_group_id": 1163
    },
    "comment": "Job run at Mon May 05 at 09:42 on (k172:ncpus=12:ngpus=1:mem=1048576kb)",
    "etime": "Mon May  5 07:28:56 2025",
    "run_count": 1,
    "eligible_time": "02:13:25",
    "Submit_arguments": "-N 10128 /tmp/10128.NBYXyCl",
    "estimated": {
      "exec_vnode": "(k172:ncpus=12:ngpus=1:mem=1048576kb)",
      "start_time": "Mon May  5 09:50:00 2025"
    },
    "project": "_pbs_project_default",
    "Submit_Host": "katana3"
  },
  {
    "Job_Name": 10129,
    "Job_Owner": "z5382435@katana1",
    "resources_used": {
      "cpupercent": 1164,
      "cput": "13:32:52",
      "fs_usage": 816,
      "mem": "146768kb",
      "ncpus": 12,
      "vmem": "146768kb",
      "walltime": "01:08:35"
    },
    "job_state": "R",
    "queue": "generalgpu12",
    "server": "kman",
    "Checkpoint": "u",
    "ctime": "Mon May  5 07:30:28 2025",
    "Error_Path": "katana1:/srv/scratch/z5382435/.automated/10129/10129.e6495024",
    "exec_host": "k103/1*12",
    "exec_vnode": "(k103:ncpus=12:ngpus=1:mem=1048576kb)",
    "Hold_Types": "n",
    "Join_Path": "oe",
    "Keep_Files": "n",
    "Mail_Points": "a",
    "mtime": "Mon May  5 11:00:29 2025",
    "Output_Path": "katana1:/srv/scratch/z5382435/.automated/10129/10129.o6495024",
    "Priority": 0,
    "qtime": "Mon May  5 07:30:28 2025",
    "Rerunable": "True",
    "Resource_List": {
      "ib": "no",
      "mem": "1gb",
      "ncpus": 12,
      "ngpus": 1,
      "nodect": 1,
      "place": "group=generalgpu12",
      "select": "ncpus=12:ngpus=1:mem=1gb",
      "walltime": "12:00:00"
    },
    "stime": "Mon May  5 09:51:52 2025",
    "session_id": 2656592,
    "jobdir": "/home/z5382435",
    "substate": 42,
    "Variable_List": {
      "PBS_O_HOME": "/home/z5382435",
      "PBS_O_LANG": "en_AU.UTF-8",
      "PBS_O_LOGNAME": "z5382435",
      "PBS_O_PATH": "/srv/scratch/z5382435/anaconda3/bin:/home/z5382435/bin:/usr/share/Modules/bin:/usr/lib64/ccache:/usr/local/bin:/usr/bin:/usr/local/sbin:/usr/sbin:/opt/pbs/bin",
      "PBS_O_SHELL": "/bin/bash",
      "PBS_O_WORKDIR": "/srv/scratch/z5382435/.automated/10129",
      "PBS_O_SYSTEM": "Linux",
      "PBS_O_QUEUE": "generalgpu12",
      "PBS_O_HOST": "katana1",
      "nvidia_group_id": 834
    },
    "comment": "Job run at Mon May 05 at 09:51 on (k103:ncpus=12:ngpus=1:mem=1048576kb)",
    "etime": "Mon May  5 07:30:28 2025",
    "run_count": 1,
    "eligible_time": "02:21:28",
    "Submit_arguments": "-N 10129 /tmp/10129.ypkNrf2",
    "estimated": {
      "exec_vnode": "(k103:ncpus=12:ngpus=1:mem=1048576kb)",
      "start_time": "Mon May  5 10:00:00 2025"
    },
    "project": "_pbs_project_default",
    "Submit_Host": "katana1"
  },
  {
    "Job_Name": 10132,
    "Job_Owner": "z5382435@katana1",
    "resources_used": {
      "cpupercent": 1169,
      "cput": "11:58:06",
      "fs_usage": 708,
      "mem": "136480kb",
      "ncpus": 12,
      "vmem": "136480kb",
      "walltime": "01:00:36"
    },
    "job_state": "R",
    "queue": "generalgpu12",
    "server": "kman",
    "Checkpoint": "u",
    "ctime": "Mon May  5 08:13:08 2025",
    "Error_Path": "katana1:/srv/scratch/z5382435/.automated/10132/10132.e6495046",
    "exec_host": "k092/2*12",
    "exec_vnode": "(k092:ncpus=12:ngpus=1:mem=1048576kb)",
    "Hold_Types": "n",
    "Join_Path": "oe",
    "Keep_Files": "n",
    "Mail_Points": "a",
    "mtime": "Mon May  5 11:00:35 2025",
    "Output_Path": "katana1:/srv/scratch/z5382435/.automated/10132/10132.o6495046",
    "Priority": 0,
    "qtime": "Mon May  5 08:13:08 2025",
    "Rerunable": "True",
    "Resource_List": {
      "ib": "no",
      "mem": "1gb",
      "ncpus": 12,
      "ngpus": 1,
      "nodect": 1,
      "place": "group=generalgpu12",
      "select": "ncpus=12:ngpus=1:mem=1gb",
      "walltime": "12:00:00"
    },
    "stime": "Mon May  5 09:59:56 2025",
    "session_id": 742089,
    "jobdir": "/home/z5382435",
    "substate": 42,
    "Variable_List": {
      "PBS_O_HOME": "/home/z5382435",
      "PBS_O_LANG": "en_AU.UTF-8",
      "PBS_O_LOGNAME": "z5382435",
      "PBS_O_PATH": "/srv/scratch/z5382435/anaconda3/bin:/home/z5382435/bin:/usr/share/Modules/bin:/usr/lib64/ccache:/usr/local/bin:/usr/bin:/usr/local/sbin:/usr/sbin:/opt/pbs/bin",
      "PBS_O_SHELL": "/bin/bash",
      "PBS_O_WORKDIR": "/srv/scratch/z5382435/.automated/10132",
      "PBS_O_SYSTEM": "Linux",
      "PBS_O_QUEUE": "generalgpu12",
      "PBS_O_HOST": "katana1",
      "nvidia_group_id": 1089
    },
    "comment": "Job run at Mon May 05 at 09:59 on (k092:ncpus=12:ngpus=1:mem=1048576kb)",
    "etime": "Mon May  5 08:13:08 2025",
    "run_count": 1,
    "eligible_time": "01:46:52",
    "Submit_arguments": "-N 10132 /tmp/10132.LyyfxLd",
    "estimated": {
      "exec_vnode": "(k092:ncpus=12:ngpus=1:mem=1048576kb)",
      "start_time": "Mon May  5 09:59:46 2025"
    },
    "project": "_pbs_project_default",
    "Submit_Host": "katana1"
  },
  {
    "Job_Name": 10134,
    "Job_Owner": "z5382435@katana3",
    "resources_used": {
      "cpupercent": 1155,
      "cput": "09:52:23",
      "fs_usage": 588,
      "mem": "201852kb",
      "ncpus": 12,
      "vmem": "201852kb",
      "walltime": "00:50:28"
    },
    "job_state": "R",
    "queue": "generalgpu12",
    "server": "kman",
    "Checkpoint": "u",
    "ctime": "Mon May  5 08:48:30 2025",
    "Error_Path": "katana3:/srv/scratch/z5382435/.automated/10134/10134.e6495052",
    "exec_host": "k106/0*12",
    "exec_vnode": "(k106:ncpus=12:ngpus=1:mem=1048576kb)",
    "Hold_Types": "n",
    "Join_Path": "oe",
    "Keep_Files": "n",
    "Mail_Points": "a",
    "mtime": "Mon May  5 10:59:03 2025",
    "Output_Path": "katana3:/srv/scratch/z5382435/.automated/10134/10134.o6495052",
    "Priority": 0,
    "qtime": "Mon May  5 08:48:30 2025",
    "Rerunable": "True",
    "Resource_List": {
      "ib": "no",
      "mem": "1gb",
      "ncpus": 12,
      "ngpus": 1,
      "nodect": 1,
      "place": "group=generalgpu12",
      "select": "ncpus=12:ngpus=1:mem=1gb",
      "walltime": "12:00:00"
    },
    "stime": "Mon May  5 10:08:33 2025",
    "session_id": 4075789,
    "jobdir": "/home/z5382435",
    "substate": 42,
    "Variable_List": {
      "PBS_O_HOME": "/home/z5382435",
      "PBS_O_LANG": "en_AU.UTF-8",
      "PBS_O_LOGNAME": "z5382435",
      "PBS_O_PATH": "/srv/scratch/z5382435/anaconda3/bin:/home/z5382435/bin:/usr/share/Modules/bin:/usr/lib64/ccache:/usr/local/bin:/usr/bin:/usr/local/sbin:/usr/sbin:/opt/pbs/bin",
      "PBS_O_SHELL": "/bin/bash",
      "PBS_O_WORKDIR": "/srv/scratch/z5382435/.automated/10134",
      "PBS_O_SYSTEM": "Linux",
      "PBS_O_QUEUE": "generalgpu12",
      "PBS_O_HOST": "katana3",
      "nvidia_group_id": 1098
    },
    "comment": "Job run at Mon May 05 at 10:08 on (k106:ncpus=12:ngpus=1:mem=1048576kb)",
    "etime": "Mon May  5 08:48:30 2025",
    "run_count": 1,
    "eligible_time": "01:20:07",
    "Submit_arguments": "-N 10134 /tmp/10134.ySGYkzR",
    "estimated": {
      "exec_vnode": "(k106:ncpus=12:ngpus=1:mem=1048576kb)",
      "start_time": "Mon May  5 10:08:24 2025"
    },
    "project": "_pbs_project_default",
    "Submit_Host": "katana3"
  },
  {
    "Job_Name": 10136,
    "Job_Owner": "z5382435@katana1",
    "resources_used": {
      "cpupercent": 1138,
      "cput": "08:12:37",
      "fs_usage": 492,
      "mem": "123348kb",
      "ncpus": 12,
      "vmem": "123348kb",
      "walltime": "00:42:24"
    },
    "job_state": "R",
    "queue": "generalgpu12",
    "server": "kman",
    "Checkpoint": "u",
    "ctime": "Mon May  5 09:33:08 2025",
    "Error_Path": "katana1:/srv/scratch/z5382435/.automated/10136/10136.e6495066",
    "exec_host": "k091/2*12",
    "exec_vnode": "(k091:ncpus=12:ngpus=1:mem=1048576kb)",
    "Hold_Types": "n",
    "Join_Path": "oe",
    "Keep_Files": "n",
    "Mail_Points": "a",
    "mtime": "Mon May  5 11:00:24 2025",
    "Output_Path": "katana1:/srv/scratch/z5382435/.automated/10136/10136.o6495066",
    "Priority": 0,
    "qtime": "Mon May  5 09:33:08 2025",
    "Rerunable": "True",
    "Resource_List": {
      "ib": "no",
      "mem": "1gb",
      "ncpus": 12,
      "ngpus": 1,
      "nodect": 1,
      "place": "group=generalgpu12",
      "select": "ncpus=12:ngpus=1:mem=1gb",
      "walltime": "12:00:00"
    },
    "stime": "Mon May  5 10:17:57 2025",
    "session_id": 584884,
    "jobdir": "/home/z5382435",
    "substate": 42,
    "Variable_List": {
      "PBS_O_HOME": "/home/z5382435",
      "PBS_O_LANG": "en_AU.UTF-8",
      "PBS_O_LOGNAME": "z5382435",
      "PBS_O_PATH": "/srv/scratch/z5382435/anaconda3/bin:/home/z5382435/bin:/usr/share/Modules/bin:/usr/lib64/ccache:/usr/local/bin:/usr/bin:/usr/local/sbin:/usr/sbin:/opt/pbs/bin",
      "PBS_O_SHELL": "/bin/bash",
      "PBS_O_WORKDIR": "/srv/scratch/z5382435/.automated/10136",
      "PBS_O_SYSTEM": "Linux",
      "PBS_O_QUEUE": "generalgpu12",
      "PBS_O_HOST": "katana1",
      "nvidia_group_id": 718
    },
    "comment": "Job run at Mon May 05 at 10:17 on (k091:ncpus=12:ngpus=1:mem=1048576kb)",
    "etime": "Mon May  5 09:33:08 2025",
    "run_count": 1,
    "eligible_time": "00:44:53",
    "Submit_arguments": "-N 10136 /tmp/10136.SiTNqTf",
    "estimated": {
      "exec_vnode": "(k091:ncpus=12:ngpus=1:mem=1048576kb)",
      "start_time": "Mon May  5 10:19:58 2025"
    },
    "project": "_pbs_project_default",
    "Submit_Host": "katana1"
  },
  {
    "Job_Name": 10138,
    "Job_Owner": "z5382435@katana1",
    "job_state": "Q",
    "queue": "generalgpu12",
    "server": "kman",
    "Checkpoint": "u",
    "ctime": "Mon May  5 09:42:53 2025",
    "Error_Path": "katana1:/srv/scratch/z5382435/.automated/10138/10138.e6495078",
    "Hold_Types": "n",
    "Join_Path": "oe",
    "Keep_Files": "n",
    "Mail_Points": "a",
    "mtime": "Mon May  5 11:00:46 2025",
    "Output_Path": "katana1:/srv/scratch/z5382435/.automated/10138/10138.o6495078",
    "Priority": 0,
    "qtime": "Mon May  5 09:42:53 2025",
    "Rerunable": "True",
    "Resource_List": {
      "ib": "no",
      "mem": "1gb",
      "ncpus": 12,
      "ngpus": 1,
      "nodect": 1,
      "place": "group=generalgpu12",
      "select": "ncpus=12:ngpus=1:mem=1gb",
      "walltime": "12:00:00"
    },
    "substate": 10,
    "Variable_List": {
      "PBS_O_HOME": "/home/z5382435",
      "PBS_O_LANG": "en_AU.UTF-8",
      "PBS_O_LOGNAME": "z5382435",
      "PBS_O_PATH": "/srv/scratch/z5382435/anaconda3/bin:/home/z5382435/bin:/usr/share/Modules/bin:/usr/lib64/ccache:/usr/local/bin:/usr/bin:/usr/local/sbin:/usr/sbin:/opt/pbs/bin",
      "PBS_O_SHELL": "/bin/bash",
      "PBS_O_WORKDIR": "/srv/scratch/z5382435/.automated/10138",
      "PBS_O_SYSTEM": "Linux",
      "PBS_O_QUEUE": "generalgpu12",
      "PBS_O_HOST": "katana1"
    },
    "comment": "Not Running: Insufficient amount of resource: ncpus ",
    "etime": "Mon May  5 09:42:53 2025",
    "eligible_time": "01:17:58",
    "Submit_arguments": "-N 10138 /tmp/10138.V4cZ6dk",
    "estimated": {
      "exec_vnode": "(k173:ncpus=12:ngpus=1:mem=1048576kb)",
      "start_time": "Mon May  5 15:50:50 2025"
    },
    "project": "_pbs_project_default",
    "Submit_Host": "katana1"
  },
  {
    "Job_Name": 10139,
    "Job_Owner": "z5382435@katana1",
    "job_state": "Q",
    "queue": "generalgpu12",
    "server": "kman",
    "Checkpoint": "u",
    "ctime": "Mon May  5 09:52:40 2025",
    "Error_Path": "katana1:/srv/scratch/z5382435/.automated/10139/10139.e6495094",
    "Hold_Types": "n",
    "Join_Path": "oe",
    "Keep_Files": "n",
    "Mail_Points": "a",
    "mtime": "Mon May  5 11:00:46 2025",
    "Output_Path": "katana1:/srv/scratch/z5382435/.automated/10139/10139.o6495094",
    "Priority": 0,
    "qtime": "Mon May  5 09:52:41 2025",
    "Rerunable": "True",
    "Resource_List": {
      "ib": "no",
      "mem": "1gb",
      "ncpus": 12,
      "ngpus": 1,
      "nodect": 1,
      "place": "group=generalgpu12",
      "select": "ncpus=12:ngpus=1:mem=1gb",
      "walltime": "12:00:00"
    },
    "substate": 10,
    "Variable_List": {
      "PBS_O_HOME": "/home/z5382435",
      "PBS_O_LANG": "en_AU.UTF-8",
      "PBS_O_LOGNAME": "z5382435",
      "PBS_O_PATH": "/srv/scratch/z5382435/anaconda3/bin:/home/z5382435/bin:/usr/share/Modules/bin:/usr/lib64/ccache:/usr/local/bin:/usr/bin:/usr/local/sbin:/usr/sbin:/opt/pbs/bin",
      "PBS_O_SHELL": "/bin/bash",
      "PBS_O_WORKDIR": "/srv/scratch/z5382435/.automated/10139",
      "PBS_O_SYSTEM": "Linux",
      "PBS_O_QUEUE": "generalgpu12",
      "PBS_O_HOST": "katana1"
    },
    "comment": "Not Running: Insufficient amount of resource: ncpus ",
    "etime": "Mon May  5 09:52:41 2025",
    "eligible_time": "01:08:11",
    "Submit_arguments": "-N 10139 /tmp/10139.7wagS3E",
    "estimated": {
      "exec_vnode": "(k173:ncpus=12:ngpus=1:mem=1048576kb)",
      "start_time": "Mon May  5 19:46:19 2025"
    },
    "project": "_pbs_project_default",
    "Submit_Host": "katana1"
  },
  {
    "Job_Name": 10142,
    "Job_Owner": "z5382435@katana3",
    "job_state": "Q",
    "queue": "generalgpu12",
    "server": "kman",
    "Checkpoint": "u",
    "ctime": "Mon May  5 10:00:55 2025",
    "Error_Path": "katana3:/srv/scratch/z5382435/.automated/10142/10142.e6495104",
    "Hold_Types": "n",
    "Join_Path": "oe",
    "Keep_Files": "n",
    "Mail_Points": "a",
    "mtime": "Mon May  5 11:00:47 2025",
    "Output_Path": "katana3:/srv/scratch/z5382435/.automated/10142/10142.o6495104",
    "Priority": 0,
    "qtime": "Mon May  5 10:00:55 2025",
    "Rerunable": "True",
    "Resource_List": {
      "ib": "no",
      "mem": "1gb",
      "ncpus": 12,
      "ngpus": 1,
      "nodect": 1,
      "place": "group=generalgpu12",
      "select": "ncpus=12:ngpus=1:mem=1gb",
      "walltime": "12:00:00"
    },
    "substate": 10,
    "Variable_List": {
      "PBS_O_HOME": "/home/z5382435",
      "PBS_O_LANG": "en_AU.UTF-8",
      "PBS_O_LOGNAME": "z5382435",
      "PBS_O_PATH": "/srv/scratch/z5382435/anaconda3/bin:/home/z5382435/bin:/usr/share/Modules/bin:/usr/lib64/ccache:/usr/local/bin:/usr/bin:/usr/local/sbin:/usr/sbin:/opt/pbs/bin",
      "PBS_O_SHELL": "/bin/bash",
      "PBS_O_WORKDIR": "/srv/scratch/z5382435/.automated/10142",
      "PBS_O_SYSTEM": "Linux",
      "PBS_O_QUEUE": "generalgpu12",
      "PBS_O_HOST": "katana3"
    },
    "comment": "Not Running: Insufficient amount of resource: ncpus ",
    "etime": "Mon May  5 10:00:55 2025",
    "eligible_time": "00:59:56",
    "Submit_arguments": "-N 10142 /tmp/10142.my16Uze",
    "estimated": {
      "exec_vnode": "(k201:ncpus=12:ngpus=1:mem=1048576kb)",
      "start_time": "Mon May  5 20:19:15 2025"
    },
    "project": "_pbs_project_default",
    "Submit_Host": "katana3"
  },
  {
    "Job_Name": 10144,
    "Job_Owner": "z5382435@katana2",
    "job_state": "Q",
    "queue": "generalgpu12",
    "server": "kman",
    "Checkpoint": "u",
    "ctime": "Mon May  5 10:09:09 2025",
    "Error_Path": "katana2:/srv/scratch/z5382435/.automated/10144/10144.e6495111",
    "Hold_Types": "n",
    "Join_Path": "oe",
    "Keep_Files": "n",
    "Mail_Points": "a",
    "mtime": "Mon May  5 10:09:15 2025",
    "Output_Path": "katana2:/srv/scratch/z5382435/.automated/10144/10144.o6495111",
    "Priority": 0,
    "qtime": "Mon May  5 10:09:09 2025",
    "Rerunable": "True",
    "Resource_List": {
      "ib": "no",
      "mem": "1gb",
      "ncpus": 12,
      "ngpus": 1,
      "nodect": 1,
      "place": "group=generalgpu12",
      "select": "ncpus=12:ngpus=1:mem=1gb",
      "walltime": "12:00:00"
    },
    "substate": 10,
    "Variable_List": {
      "PBS_O_HOME": "/home/z5382435",
      "PBS_O_LANG": "en_AU.UTF-8",
      "PBS_O_LOGNAME": "z5382435",
      "PBS_O_PATH": "/srv/scratch/z5382435/anaconda3/bin:/home/z5382435/bin:/usr/share/Modules/bin:/usr/lib64/ccache:/usr/local/bin:/usr/bin:/usr/local/sbin:/usr/sbin:/opt/pbs/bin",
      "PBS_O_SHELL": "/bin/bash",
      "PBS_O_WORKDIR": "/srv/scratch/z5382435/.automated/10144",
      "PBS_O_SYSTEM": "Linux",
      "PBS_O_QUEUE": "generalgpu12",
      "PBS_O_HOST": "katana2"
    },
    "comment": "Not Running: Insufficient amount of resource: ncpus ",
    "etime": "Mon May  5 10:09:09 2025",
    "eligible_time": "00:51:42",
    "Submit_arguments": "-N 10144 /tmp/10144.GViPSV2",
    "project": "_pbs_project_default",
    "Submit_Host": "katana2"
  },
  {
    "Job_Name": 10146,
    "Job_Owner": "z5382435@katana1",
    "job_state": "Q",
    "queue": "generalgpu12",
    "server": "kman",
    "Checkpoint": "u",
    "ctime": "Mon May  5 10:18:55 2025",
    "Error_Path": "katana1:/srv/scratch/z5382435/.automated/10146/10146.e6495124",
    "Hold_Types": "n",
    "Join_Path": "oe",
    "Keep_Files": "n",
    "Mail_Points": "a",
    "mtime": "Mon May  5 10:19:03 2025",
    "Output_Path": "katana1:/srv/scratch/z5382435/.automated/10146/10146.o6495124",
    "Priority": 0,
    "qtime": "Mon May  5 10:18:55 2025",
    "Rerunable": "True",
    "Resource_List": {
      "ib": "no",
      "mem": "1gb",
      "ncpus": 12,
      "ngpus": 1,
      "nodect": 1,
      "place": "group=generalgpu12",
      "select": "ncpus=12:ngpus=1:mem=1gb",
      "walltime": "12:00:00"
    },
    "substate": 10,
    "Variable_List": {
      "PBS_O_HOME": "/home/z5382435",
      "PBS_O_LANG": "en_AU.UTF-8",
      "PBS_O_LOGNAME": "z5382435",
      "PBS_O_PATH": "/srv/scratch/z5382435/anaconda3/bin:/home/z5382435/bin:/usr/share/Modules/bin:/usr/lib64/ccache:/usr/local/bin:/usr/bin:/usr/local/sbin:/usr/sbin:/opt/pbs/bin",
      "PBS_O_SHELL": "/bin/bash",
      "PBS_O_WORKDIR": "/srv/scratch/z5382435/.automated/10146",
      "PBS_O_SYSTEM": "Linux",
      "PBS_O_QUEUE": "generalgpu12",
      "PBS_O_HOST": "katana1"
    },
    "comment": "Not Running: Insufficient amount of resource: ncpus ",
    "etime": "Mon May  5 10:18:55 2025",
    "eligible_time": "00:41:56",
    "Submit_arguments": "-N 10146 /tmp/10146.juxjf8Z",
    "project": "_pbs_project_default",
    "Submit_Host": "katana1"
  }
]
