[
  {
    "Job_Name": 14978,
    "Job_Owner": "z5358697@katana1",
    "resources_used": {
      "cpupercent": 1566,
      "cput": "35:32:25",
      "fs_usage": 2160,
      "mem": "99956kb",
      "ncpus": 16,
      "vmem": "99956kb",
      "walltime": "02:16:07"
    },
    "job_state": "R",
    "queue": "cstudent12",
    "server": "kman",
    "Checkpoint": "u",
    "ctime": "Wed Jun 25 11:12:04 2025",
    "Error_Path": "katana1:/srv/scratch/z5358697/.automated/14978/14978.e6642490",
    "exec_host": "k182/5*16",
    "exec_vnode": "(k182:ncpus=16:mem=1048576kb:ngpus=0)",
    "Hold_Types": "n",
    "Join_Path": "oe",
    "Keep_Files": "n",
    "Mail_Points": "a",
    "mtime": "Wed Jun 25 14:46:09 2025",
    "Output_Path": "katana1:/srv/scratch/z5358697/.automated/14978/14978.o6642490",
    "Priority": 0,
    "qtime": "Wed Jun 25 11:12:04 2025",
    "Rerunable": "True",
    "Resource_List": {
      "ib": "no",
      "mem": "1gb",
      "ncpus": 16,
      "ngpus": 0,
      "nodect": 1,
      "place": "group=cstudent12",
      "select": "cputype=sapphirerapids:ncpus=16:mem=1gb",
      "walltime": "12:00:00"
    },
    "stime": "Wed Jun 25 12:29:58 2025",
    "session_id": 866602,
    "jobdir": "/home/z5358697",
    "substate": 42,
    "Variable_List": {
      "PBS_O_HOME": "/home/z5358697",
      "PBS_O_LANG": "en_AU.UTF-8",
      "PBS_O_LOGNAME": "z5358697",
      "PBS_O_PATH": "/apps/z_install_tree/linux-rocky8-ivybridge/gcc-12.2.0/python-3.10.8-pmtwsrrmcmrs6olvgx5xhepgh7gl5vro/bin:/home/z5358697/bin:/home/z5358697/bin:/usr/share/Modules/bin:/usr/lib64/ccache:/usr/local/bin:/usr/bin:/usr/local/sbin:/usr/sbin:/opt/pbs/bin",
      "PBS_O_SHELL": "/bin/bash",
      "PBS_O_WORKDIR": "/srv/scratch/z5358697/.automated/14978",
      "PBS_O_SYSTEM": "Linux",
      "PBS_O_QUEUE": "cstudent12",
      "PBS_O_HOST": "katana1"
    },
    "comment": "Job run at Wed Jun 25 at 12:29 on (k182:ncpus=16:mem=1048576kb:ngpus=0)",
    "etime": "Wed Jun 25 11:12:04 2025",
    "run_count": 1,
    "eligible_time": "01:17:57",
    "Submit_arguments": "-N 14978 /tmp/14978.6CbgEcH",
    "estimated": {
      "exec_vnode": "(k182:ncpus=16:mem=1048576kb:ngpus=0)",
      "start_time": "Wed Jun 25 12:59:59 2025"
    },
    "project": "_pbs_project_default",
    "Submit_Host": "katana1"
  },
  {
    "Job_Name": 14984,
    "Job_Owner": "z5358697@katana1",
    "resources_used": {
      "cpupercent": 1471,
      "cput": "07:13:51",
      "fs_usage": 432,
      "mem": "112288kb",
      "ncpus": 16,
      "vmem": "112288kb",
      "walltime": "00:28:24"
    },
    "job_state": "R",
    "queue": "cstudent12",
    "server": "kman",
    "Checkpoint": "u",
    "ctime": "Wed Jun 25 11:32:31 2025",
    "Error_Path": "katana1:/srv/scratch/z5358697/.automated/14984/14984.e6642518",
    "exec_host": "k020/2*16",
    "exec_vnode": "(k020:ncpus=16:mem=1048576kb:ngpus=0)",
    "Hold_Types": "n",
    "Join_Path": "oe",
    "Keep_Files": "n",
    "Mail_Points": "a",
    "mtime": "Wed Jun 25 14:45:32 2025",
    "Output_Path": "katana1:/srv/scratch/z5358697/.automated/14984/14984.o6642518",
    "Priority": 0,
    "qtime": "Wed Jun 25 11:32:32 2025",
    "Rerunable": "True",
    "Resource_List": {
      "ib": "no",
      "mem": "1gb",
      "ncpus": 16,
      "ngpus": 0,
      "nodect": 1,
      "place": "group=cstudent12",
      "select": "cpuflags=avx512f:ncpus=16:mem=1gb",
      "walltime": "12:00:00"
    },
    "stime": "Wed Jun 25 14:17:06 2025",
    "session_id": 749092,
    "jobdir": "/home/z5358697",
    "substate": 42,
    "Variable_List": {
      "PBS_O_HOME": "/home/z5358697",
      "PBS_O_LANG": "en_AU.UTF-8",
      "PBS_O_LOGNAME": "z5358697",
      "PBS_O_PATH": "/apps/z_install_tree/linux-rocky8-ivybridge/gcc-12.2.0/python-3.10.8-pmtwsrrmcmrs6olvgx5xhepgh7gl5vro/bin:/home/z5358697/bin:/home/z5358697/bin:/usr/share/Modules/bin:/usr/lib64/ccache:/usr/local/bin:/usr/bin:/usr/local/sbin:/usr/sbin:/opt/pbs/bin",
      "PBS_O_SHELL": "/bin/bash",
      "PBS_O_WORKDIR": "/srv/scratch/z5358697/.automated/14984",
      "PBS_O_SYSTEM": "Linux",
      "PBS_O_QUEUE": "cstudent12",
      "PBS_O_HOST": "katana1"
    },
    "comment": "Job run at Wed Jun 25 at 14:17 on (k020:ncpus=16:mem=1048576kb:ngpus=0)",
    "etime": "Wed Jun 25 11:32:32 2025",
    "run_count": 1,
    "eligible_time": "02:44:38",
    "Submit_arguments": "-N 14984 /tmp/14984.zwBRlK7",
    "estimated": {
      "exec_vnode": "(k136:ncpus=16:mem=1048576kb:ngpus=0)",
      "start_time": "Wed Jun 25 14:19:49 2025"
    },
    "project": "_pbs_project_default",
    "Submit_Host": "katana1"
  },
  {
    "Job_Name": 14985,
    "Job_Owner": "z5358697@katana3",
    "resources_used": {
      "cpupercent": 1438,
      "cput": "05:52:00",
      "fs_usage": 352,
      "mem": "114920kb",
      "ncpus": 16,
      "vmem": "114920kb",
      "walltime": "00:23:47"
    },
    "job_state": "R",
    "queue": "cstudent12",
    "server": "kman",
    "Checkpoint": "u",
    "ctime": "Wed Jun 25 11:36:25 2025",
    "Error_Path": "katana3:/srv/scratch/z5358697/.automated/14985/14985.e6642524",
    "exec_host": "k016/0*16",
    "exec_vnode": "(k016:ncpus=16:mem=1048576kb:ngpus=0)",
    "Hold_Types": "n",
    "Join_Path": "oe",
    "Keep_Files": "n",
    "Mail_Points": "a",
    "mtime": "Wed Jun 25 14:45:21 2025",
    "Output_Path": "katana3:/srv/scratch/z5358697/.automated/14985/14985.o6642524",
    "Priority": 0,
    "qtime": "Wed Jun 25 11:36:25 2025",
    "Rerunable": "True",
    "Resource_List": {
      "ib": "no",
      "mem": "1gb",
      "ncpus": 16,
      "ngpus": 0,
      "nodect": 1,
      "place": "group=cstudent12",
      "select": "cpuflags=avx512f:ncpus=16:mem=1gb",
      "walltime": "12:00:00"
    },
    "stime": "Wed Jun 25 14:21:31 2025",
    "session_id": 435777,
    "jobdir": "/home/z5358697",
    "substate": 42,
    "Variable_List": {
      "PBS_O_HOME": "/home/z5358697",
      "PBS_O_LANG": "en_AU.UTF-8",
      "PBS_O_LOGNAME": "z5358697",
      "PBS_O_PATH": "/apps/z_install_tree/linux-rocky8-ivybridge/gcc-12.2.0/python-3.10.8-pmtwsrrmcmrs6olvgx5xhepgh7gl5vro/bin:/home/z5358697/bin:/home/z5358697/bin:/usr/share/Modules/bin:/usr/lib64/ccache:/usr/local/bin:/usr/bin:/usr/local/sbin:/usr/sbin:/opt/pbs/bin",
      "PBS_O_SHELL": "/bin/bash",
      "PBS_O_WORKDIR": "/srv/scratch/z5358697/.automated/14985",
      "PBS_O_SYSTEM": "Linux",
      "PBS_O_QUEUE": "cstudent12",
      "PBS_O_HOST": "katana3"
    },
    "comment": "Job run at Wed Jun 25 at 14:21 on (k016:ncpus=16:mem=1048576kb:ngpus=0)",
    "etime": "Wed Jun 25 11:36:25 2025",
    "run_count": 1,
    "eligible_time": "02:45:10",
    "Submit_arguments": "-N 14985 /tmp/14985.eNosAfO",
    "estimated": {
      "exec_vnode": "(k155:ncpus=16:mem=1048576kb:ngpus=0)",
      "start_time": "Wed Jun 25 14:37:39 2025"
    },
    "project": "_pbs_project_default",
    "Submit_Host": "katana3"
  },
  {
    "Job_Name": 14988,
    "Job_Owner": "z5358697@katana1",
    "resources_used": {
      "cpupercent": 1456,
      "cput": "05:38:03",
      "fs_usage": 320,
      "mem": "113156kb",
      "ncpus": 16,
      "vmem": "113156kb",
      "walltime": "00:21:37"
    },
    "job_state": "R",
    "queue": "cstudent12",
    "server": "kman",
    "Checkpoint": "u",
    "ctime": "Wed Jun 25 11:47:43 2025",
    "Error_Path": "katana1:/srv/scratch/z5358697/.automated/14988/14988.e6642540",
    "exec_host": "k161/0*16",
    "exec_vnode": "(k161:ncpus=16:mem=1048576kb:ngpus=0)",
    "Hold_Types": "n",
    "Join_Path": "oe",
    "Keep_Files": "n",
    "Mail_Points": "a",
    "mtime": "Wed Jun 25 14:46:26 2025",
    "Output_Path": "katana1:/srv/scratch/z5358697/.automated/14988/14988.o6642540",
    "Priority": 0,
    "qtime": "Wed Jun 25 11:47:44 2025",
    "Rerunable": "True",
    "Resource_List": {
      "ib": "no",
      "mem": "1gb",
      "ncpus": 16,
      "ngpus": 0,
      "nodect": 1,
      "place": "group=cstudent12",
      "select": "cpuflags=avx512f:ncpus=16:mem=1gb",
      "walltime": "12:00:00"
    },
    "stime": "Wed Jun 25 14:24:47 2025",
    "session_id": 100491,
    "jobdir": "/home/z5358697",
    "substate": 42,
    "Variable_List": {
      "PBS_O_HOME": "/home/z5358697",
      "PBS_O_LANG": "en_AU.UTF-8",
      "PBS_O_LOGNAME": "z5358697",
      "PBS_O_PATH": "/apps/z_install_tree/linux-rocky8-ivybridge/gcc-12.2.0/python-3.10.8-pmtwsrrmcmrs6olvgx5xhepgh7gl5vro/bin:/home/z5358697/bin:/home/z5358697/bin:/usr/share/Modules/bin:/usr/lib64/ccache:/usr/local/bin:/usr/bin:/usr/local/sbin:/usr/sbin:/opt/pbs/bin",
      "PBS_O_SHELL": "/bin/bash",
      "PBS_O_WORKDIR": "/srv/scratch/z5358697/.automated/14988",
      "PBS_O_SYSTEM": "Linux",
      "PBS_O_QUEUE": "cstudent12",
      "PBS_O_HOST": "katana1"
    },
    "comment": "Job run at Wed Jun 25 at 14:24 on (k161:ncpus=16:mem=1048576kb:ngpus=0)",
    "etime": "Wed Jun 25 11:47:44 2025",
    "run_count": 1,
    "eligible_time": "02:37:07",
    "Submit_arguments": "-N 14988 /tmp/14988.iHZQSps",
    "estimated": {
      "exec_vnode": "(k155:ncpus=16:mem=1048576kb:ngpus=0)",
      "start_time": "Wed Jun 25 14:37:39 2025"
    },
    "project": "_pbs_project_default",
    "Submit_Host": "katana1"
  },
  {
    "Job_Name": 14992,
    "Job_Owner": "z5358697@katana1",
    "job_state": "Q",
    "queue": "cstudent12",
    "server": "kman",
    "Checkpoint": "u",
    "ctime": "Wed Jun 25 12:41:04 2025",
    "Error_Path": "katana1:/srv/scratch/z5358697/.automated/14992/14992.e6642613",
    "Hold_Types": "n",
    "Join_Path": "oe",
    "Keep_Files": "n",
    "Mail_Points": "a",
    "mtime": "Wed Jun 25 14:46:16 2025",
    "Output_Path": "katana1:/srv/scratch/z5358697/.automated/14992/14992.o6642613",
    "Priority": 0,
    "qtime": "Wed Jun 25 12:41:04 2025",
    "Rerunable": "True",
    "Resource_List": {
      "ib": "no",
      "mem": "1gb",
      "ncpus": 16,
      "ngpus": 0,
      "nodect": 1,
      "place": "group=cstudent12",
      "select": "cputype=sapphirerapids:ncpus=16:mem=1gb",
      "walltime": "12:00:00"
    },
    "substate": 10,
    "Variable_List": {
      "PBS_O_HOME": "/home/z5358697",
      "PBS_O_LANG": "en_AU.UTF-8",
      "PBS_O_LOGNAME": "z5358697",
      "PBS_O_PATH": "/apps/z_install_tree/linux-rocky8-ivybridge/gcc-12.2.0/python-3.10.8-pmtwsrrmcmrs6olvgx5xhepgh7gl5vro/bin:/home/z5358697/bin:/home/z5358697/bin:/usr/share/Modules/bin:/usr/lib64/ccache:/usr/local/bin:/usr/bin:/usr/local/sbin:/usr/sbin:/opt/pbs/bin",
      "PBS_O_SHELL": "/bin/bash",
      "PBS_O_WORKDIR": "/srv/scratch/z5358697/.automated/14992",
      "PBS_O_SYSTEM": "Linux",
      "PBS_O_QUEUE": "cstudent12",
      "PBS_O_HOST": "katana1"
    },
    "comment": "Not Running: Insufficient amount of resource: cputype ",
    "etime": "Wed Jun 25 12:41:04 2025",
    "eligible_time": "02:05:23",
    "Submit_arguments": "-N 14992 /tmp/14992.i04Dehz",
    "estimated": {
      "exec_vnode": "(k182:ncpus=16:mem=1048576kb:ngpus=0)",
      "start_time": "Wed Jun 25 16:19:05 2025"
    },
    "project": "_pbs_project_default",
    "Submit_Host": "katana1"
  },
  {
    "Job_Name": 15011,
    "Job_Owner": "z5358697@katana1",
    "job_state": "Q",
    "queue": "cstudent12",
    "server": "kman",
    "Checkpoint": "u",
    "ctime": "Wed Jun 25 13:34:37 2025",
    "Error_Path": "katana1:/srv/scratch/z5358697/.automated/15011/15011.e6642665",
    "Hold_Types": "n",
    "Join_Path": "oe",
    "Keep_Files": "n",
    "Mail_Points": "a",
    "mtime": "Wed Jun 25 14:46:17 2025",
    "Output_Path": "katana1:/srv/scratch/z5358697/.automated/15011/15011.o6642665",
    "Priority": 0,
    "qtime": "Wed Jun 25 13:34:37 2025",
    "Rerunable": "True",
    "Resource_List": {
      "ib": "no",
      "mem": "1gb",
      "ncpus": 16,
      "ngpus": 0,
      "nodect": 1,
      "place": "group=cstudent12",
      "select": "cpuflags=avx512f:ncpus=16:mem=1gb",
      "walltime": "12:00:00"
    },
    "substate": 10,
    "Variable_List": {
      "PBS_O_HOME": "/home/z5358697",
      "PBS_O_LANG": "en_AU.UTF-8",
      "PBS_O_LOGNAME": "z5358697",
      "PBS_O_PATH": "/apps/z_install_tree/linux-rocky8-ivybridge/gcc-12.2.0/python-3.10.8-pmtwsrrmcmrs6olvgx5xhepgh7gl5vro/bin:/home/z5358697/bin:/home/z5358697/bin:/usr/share/Modules/bin:/usr/lib64/ccache:/usr/local/bin:/usr/bin:/usr/local/sbin:/usr/sbin:/opt/pbs/bin",
      "PBS_O_SHELL": "/bin/bash",
      "PBS_O_WORKDIR": "/srv/scratch/z5358697/.automated/15011",
      "PBS_O_SYSTEM": "Linux",
      "PBS_O_QUEUE": "cstudent12",
      "PBS_O_HOST": "katana1"
    },
    "comment": "Not Running: Insufficient amount of resource: ncpus ",
    "etime": "Wed Jun 25 13:34:37 2025",
    "eligible_time": "01:11:50",
    "Submit_arguments": "-N 15011 /tmp/15011.TXQHuW0",
    "estimated": {
      "exec_vnode": "(k153:ncpus=16:mem=1048576kb:ngpus=0)",
      "start_time": "Wed Jun 25 15:56:26 2025"
    },
    "project": "_pbs_project_default",
    "Submit_Host": "katana1"
  },
  {
    "Job_Name": 14996,
    "Job_Owner": "z5358697@katana3",
    "job_state": "Q",
    "queue": "cstudent12",
    "server": "kman",
    "Checkpoint": "u",
    "ctime": "Wed Jun 25 14:18:12 2025",
    "Error_Path": "katana3:/srv/scratch/z5358697/.automated/14996/14996.e6642772",
    "Hold_Types": "n",
    "Join_Path": "oe",
    "Keep_Files": "n",
    "Mail_Points": "a",
    "mtime": "Wed Jun 25 14:46:17 2025",
    "Output_Path": "katana3:/srv/scratch/z5358697/.automated/14996/14996.o6642772",
    "Priority": 0,
    "qtime": "Wed Jun 25 14:18:12 2025",
    "Rerunable": "True",
    "Resource_List": {
      "ib": "no",
      "mem": "1gb",
      "ncpus": 16,
      "ngpus": 0,
      "nodect": 1,
      "place": "group=cstudent12",
      "select": "cputype=sapphirerapids:ncpus=16:mem=1gb",
      "walltime": "12:00:00"
    },
    "substate": 10,
    "Variable_List": {
      "PBS_O_HOME": "/home/z5358697",
      "PBS_O_LANG": "en_AU.UTF-8",
      "PBS_O_LOGNAME": "z5358697",
      "PBS_O_PATH": "/apps/z_install_tree/linux-rocky8-ivybridge/gcc-12.2.0/python-3.10.8-pmtwsrrmcmrs6olvgx5xhepgh7gl5vro/bin:/home/z5358697/bin:/home/z5358697/bin:/usr/share/Modules/bin:/usr/lib64/ccache:/usr/local/bin:/usr/bin:/usr/local/sbin:/usr/sbin:/opt/pbs/bin",
      "PBS_O_SHELL": "/bin/bash",
      "PBS_O_WORKDIR": "/srv/scratch/z5358697/.automated/14996",
      "PBS_O_SYSTEM": "Linux",
      "PBS_O_QUEUE": "cstudent12",
      "PBS_O_HOST": "katana3"
    },
    "comment": "Not Running: Insufficient amount of resource: cputype ",
    "etime": "Wed Jun 25 14:18:12 2025",
    "eligible_time": "00:28:15",
    "Submit_arguments": "-N 14996 /tmp/14996.2NgaS34",
    "estimated": {
      "exec_vnode": "(k209:ncpus=16:mem=1048576kb:ngpus=0)",
      "start_time": "Wed Jun 25 16:38:43 2025"
    },
    "project": "_pbs_project_default",
    "Submit_Host": "katana3"
  },
  {
    "Job_Name": 14997,
    "Job_Owner": "z5358697@katana1",
    "job_state": "Q",
    "queue": "cstudent12",
    "server": "kman",
    "Checkpoint": "u",
    "ctime": "Wed Jun 25 14:24:31 2025",
    "Error_Path": "katana1:/srv/scratch/z5358697/.automated/14997/14997.e6642782",
    "Hold_Types": "n",
    "Join_Path": "oe",
    "Keep_Files": "n",
    "Mail_Points": "a",
    "mtime": "Wed Jun 25 14:46:18 2025",
    "Output_Path": "katana1:/srv/scratch/z5358697/.automated/14997/14997.o6642782",
    "Priority": 0,
    "qtime": "Wed Jun 25 14:24:31 2025",
    "Rerunable": "True",
    "Resource_List": {
      "ib": "no",
      "mem": "1gb",
      "ncpus": 16,
      "ngpus": 0,
      "nodect": 1,
      "place": "group=cstudent12",
      "select": "cputype=sapphirerapids:ncpus=16:mem=1gb",
      "walltime": "12:00:00"
    },
    "substate": 10,
    "Variable_List": {
      "PBS_O_HOME": "/home/z5358697",
      "PBS_O_LANG": "en_AU.UTF-8",
      "PBS_O_LOGNAME": "z5358697",
      "PBS_O_PATH": "/apps/z_install_tree/linux-rocky8-ivybridge/gcc-12.2.0/python-3.10.8-pmtwsrrmcmrs6olvgx5xhepgh7gl5vro/bin:/home/z5358697/bin:/home/z5358697/bin:/usr/share/Modules/bin:/usr/lib64/ccache:/usr/local/bin:/usr/bin:/usr/local/sbin:/usr/sbin:/opt/pbs/bin",
      "PBS_O_SHELL": "/bin/bash",
      "PBS_O_WORKDIR": "/srv/scratch/z5358697/.automated/14997",
      "PBS_O_SYSTEM": "Linux",
      "PBS_O_QUEUE": "cstudent12",
      "PBS_O_HOST": "katana1"
    },
    "comment": "Not Running: Insufficient amount of resource: cputype ",
    "etime": "Wed Jun 25 14:24:31 2025",
    "eligible_time": "00:21:56",
    "Submit_arguments": "-N 14997 /tmp/14997.tjXZfd8",
    "estimated": {
      "exec_vnode": "(k208:ncpus=16:mem=1048576kb:ngpus=0)",
      "start_time": "Wed Jun 25 21:33:16 2025"
    },
    "project": "_pbs_project_default",
    "Submit_Host": "katana1"
  },
  {
    "Job_Name": 15004,
    "Job_Owner": "z5358697@katana3",
    "job_state": "Q",
    "queue": "cstudent12",
    "server": "kman",
    "Checkpoint": "u",
    "ctime": "Wed Jun 25 14:39:57 2025",
    "Error_Path": "katana3:/srv/scratch/z5358697/.automated/15004/15004.e6642792",
    "Hold_Types": "n",
    "Join_Path": "oe",
    "Keep_Files": "n",
    "Mail_Points": "a",
    "mtime": "Wed Jun 25 14:46:18 2025",
    "Output_Path": "katana3:/srv/scratch/z5358697/.automated/15004/15004.o6642792",
    "Priority": 0,
    "qtime": "Wed Jun 25 14:39:58 2025",
    "Rerunable": "True",
    "Resource_List": {
      "ib": "no",
      "mem": "1gb",
      "ncpus": 16,
      "ngpus": 0,
      "nodect": 1,
      "place": "group=cstudent12",
      "select": "cputype=sapphirerapids:ncpus=16:mem=1gb",
      "walltime": "12:00:00"
    },
    "substate": 10,
    "Variable_List": {
      "PBS_O_HOME": "/home/z5358697",
      "PBS_O_LANG": "en_AU.UTF-8",
      "PBS_O_LOGNAME": "z5358697",
      "PBS_O_PATH": "/apps/z_install_tree/linux-rocky8-ivybridge/gcc-12.2.0/python-3.10.8-pmtwsrrmcmrs6olvgx5xhepgh7gl5vro/bin:/home/z5358697/bin:/home/z5358697/bin:/usr/share/Modules/bin:/usr/lib64/ccache:/usr/local/bin:/usr/bin:/usr/local/sbin:/usr/sbin:/opt/pbs/bin",
      "PBS_O_SHELL": "/bin/bash",
      "PBS_O_WORKDIR": "/srv/scratch/z5358697/.automated/15004",
      "PBS_O_SYSTEM": "Linux",
      "PBS_O_QUEUE": "cstudent12",
      "PBS_O_HOST": "katana3"
    },
    "comment": "Not Running: Insufficient amount of resource: cputype ",
    "etime": "Wed Jun 25 14:39:58 2025",
    "eligible_time": "00:06:30",
    "Submit_arguments": "-N 15004 /tmp/15004.3ZrPmA5",
    "estimated": {
      "exec_vnode": "(k209:ncpus=16:mem=1048576kb:ngpus=0)",
      "start_time": "Wed Jun 25 21:45:28 2025"
    },
    "project": "_pbs_project_default",
    "Submit_Host": "katana3"
  },
  {
    "Job_Name": 13308,
    "Job_Owner": "z5358697@katana3",
    "job_state": "Q",
    "queue": "cstudent12",
    "server": "kman",
    "Checkpoint": "u",
    "ctime": "Wed Jun 25 14:40:10 2025",
    "Error_Path": "katana3:/home/z5358697/13308/13308.e6642793",
    "Hold_Types": "n",
    "Join_Path": "oe",
    "Keep_Files": "n",
    "Mail_Points": "a",
    "mtime": "Wed Jun 25 14:46:22 2025",
    "Output_Path": "katana3:/home/z5358697/13308/13308.o6642793",
    "Priority": 0,
    "qtime": "Wed Jun 25 14:40:10 2025",
    "Rerunable": "True",
    "Resource_List": {
      "ib": "no",
      "mem": "4gb",
      "ncpus": 1,
      "ngpus": 0,
      "nodect": 1,
      "place": "group=cstudent12",
      "select": "ncpus=1:mem=4gb",
      "walltime": "12:00:00"
    },
    "substate": 10,
    "Variable_List": {
      "PBS_O_HOME": "/home/z5358697",
      "PBS_O_LANG": "en_AU.UTF-8",
      "PBS_O_LOGNAME": "z5358697",
      "PBS_O_PATH": "/apps/z_install_tree/linux-rocky8-ivybridge/gcc-12.2.0/python-3.10.8-pmtwsrrmcmrs6olvgx5xhepgh7gl5vro/bin:/home/z5358697/bin:/home/z5358697/bin:/usr/share/Modules/bin:/usr/lib64/ccache:/usr/local/bin:/usr/bin:/usr/local/sbin:/usr/sbin:/opt/pbs/bin",
      "PBS_O_MAIL": "/var/spool/mail/z5358697",
      "PBS_O_SHELL": "/bin/bash",
      "PBS_O_WORKDIR": "/home/z5358697/13308",
      "PBS_O_SYSTEM": "Linux",
      "PBS_O_QUEUE": "cstudent12",
      "PBS_O_HOST": "katana3"
    },
    "comment": "Not Running: Placement set cstudent12=normal-all has too few free resources",
    "etime": "Wed Jun 25 14:40:10 2025",
    "eligible_time": "00:06:17",
    "Submit_arguments": "-N 13308 /tmp/13308.UHWPVIV",
    "estimated": {
      "exec_vnode": "(k158:ncpus=1:mem=4194304kb:ngpus=0)",
      "start_time": "Wed Jun 25 14:53:04 2025"
    },
    "project": "_pbs_project_default",
    "Submit_Host": "katana3"
  }
]
